[
  {
    "id": 61,
    "question": "Where is MKCL Head Office",
    "options": [
      "Mumbai",
      "Pune",
      "Nashik",
      "None"
    ],
    "answer": 1,
    "explanation": "The Correct Answer is Pune"
  },
  {
    "id": 62,
    "question": "What does MKCL stands for?",
    "options": [
      "Maharashtra Knowledge Corporation Limited",
      "Maharashtra Knowledge Center Limited",
      "Maharashtra Kerala Corporation Limited",
      "None"
    ],
    "answer": 0,
    "explanation": "The Correct Answer is Maharashtra Knowledge Corporation Limited"
  },
  {
    "id": 63,
    "question": "Which is not the Product of MKCL",
    "options": [
      "MS-CIT",
      "MOM",
      "KLIC",
      "TALLY"
    ],
    "answer": 3,
    "explanation": "The Correct Answer is TALLY"
  },
  {
    "id": 64,
    "question": "What is the old name of MS-CIT",
    "options": [
      "EASY",
      "CIT",
      "ERA",
      "None"
    ],
    "answer": 1,
    "explanation": "The Correct Answer is CIT"
  },
  {
    "id": 65,
    "question": "How many courses included in KLIC",
    "options": [
      "256",
      "200",
      "300",
      "None"
    ],
    "answer": 0,
    "explanation": "The Correct Answer is 256"
  },
  {
    "id": 66,
    "question": "Full form of MOM",
    "options": [
      "Maharashtra Online Marketing",
      "MKCL Online Marketing",
      "MKCL Olympiad Movement",
      "None"
    ],
    "answer": 2,
    "explanation": "The Correct Answer is MKCL Olympiad Movement"
  },
  {
    "id": 67,
    "question": "What is the minimum Requirement for Coordinator",
    "options": [
      "Graduate or Diploma",
      "Post Graduate",
      "12th Pass",
      "None"
    ],
    "answer": 0,
    "explanation": "The Correct Answer is Graduate or Diploma"
  },
  {
    "id": 68,
    "question": "What is the Annual Renewal Fees",
    "options": [
      "5500",
      "2500",
      "4500",
      "None"
    ],
    "answer": 0,
    "explanation": "The Correct Answer is 5500"
  },
  {
    "id": 69,
    "question": "Which Portal used for Registration of MSCIT Learner",
    "options": [
      "OES",
      "ERA",
      "SOLAR",
      "None"
    ],
    "answer": 2,
    "explanation": "The Correct Answer is SOLAR"
  },
  {
    "id": 70,
    "question": "Which software used for check Installment Ledger",
    "options": [
      "OES",
      "ERA",
      "SOLAR",
      "None"
    ],
    "answer": 2,
    "explanation": "The Correct Answer is SOLAR"
  },
  {
    "id": 71,
    "question": "Which software used for Learner Management",
    "options": [
      "OES",
      "ERA",
      "SOLAR",
      "None"
    ],
    "answer": 2,
    "explanation": "The Correct Answer is SOLAR"
  },
  {
    "id": 72,
    "question": "Which is the Exam Portal",
    "options": [
      "OES",
      "ERA",
      "SOLAR",
      "None"
    ],
    "answer": 0,
    "explanation": "The Correct Answer is OES"
  },
  {
    "id": 73,
    "question": "Which is the Learning Portal",
    "options": [
      "OES",
      "ERA",
      "SOLAR",
      "None"
    ],
    "answer": 1,
    "explanation": "The Correct Answer is ERA"
  },
  {
    "id": 74,
    "question": "Which Portal is used for Payment",
    "options": [
      "OES",
      "ERA",
      "SOLAR",
      "None"
    ],
    "answer": 2,
    "explanation": "The Correct Answer is SOLAR"
  },
  {
    "id": 75,
    "question": "What is the maximum Concurrent Users Allowed in Center",
    "options": [
      "25",
      "15",
      "20",
      "None"
    ],
    "answer": 0,
    "explanation": "The Correct Answer is 25"
  },
  {
    "id": 76,
    "question": "What is the Minimum Room Size Required",
    "options": [
      "200 Sq Ft",
      "300 Sq Ft",
      "400 Sq Ft",
      "None"
    ],
    "answer": 0,
    "explanation": "The Correct Answer is 200 Sq Ft"
  },
  {
    "id": 77,
    "question": "What is the Username for ERA Portal",
    "options": [
      "Learner ID",
      "Batch ID",
      "Center Code",
      "None"
    ],
    "answer": 0,
    "explanation": "The Correct Answer is Learner ID"
  },
  {
    "id": 78,
    "question": "What is the Username for SOLAR Portal",
    "options": [
      "Center Code",
      "Batch ID",
      "Email ID",
      "None"
    ],
    "answer": 0,
    "explanation": "The Correct Answer is Center Code"
  },
  {
    "id": 79,
    "question": "What is the Helpline Number for ERA",
    "options": [
      "020-25899600",
      "020-25899700",
      "020-25899800",
      "None"
    ],
    "answer": 0,
    "explanation": "The Correct Answer is 020-25899600"
  },
  {
    "id": 80,
    "question": "What is the Email ID for ERA Support",
    "options": [
      "erasupport@mkcl.org",
      "info@mkcl.org",
      "support@mkcl.org",
      "None"
    ],
    "answer": 0,
    "explanation": "The Correct Answer is erasupport@mkcl.org"
  },
  {
    "id": 81,
    "question": "What is the Email ID for SOLAR Support",
    "options": [
      "solarsupport@mkcl.org",
      "info@mkcl.org",
      "support@mkcl.org",
      "None"
    ],
    "answer": 0,
    "explanation": "The Correct Answer is solarsupport@mkcl.org"
  },
  {
    "id": 82,
    "question": "What is the Email ID of mkcl",
    "options": [
      "mkcl@mkcl.org",
      "info@mkcl.org",
      "support@mkcl.org",
      "None"
    ],
    "answer": 0,
    "explanation": "The Correct Answer is mkcl@mkcl.org"
  },
  {
    "id": 83,
    "question": "Which Software is used for Batch Management",
    "options": [
      "OES",
      "ERA",
      "SOLAR",
      "None"
    ],
    "answer": 2,
    "explanation": "The Correct Answer is SOLAR"
  },
  {
    "id": 84,
    "question": "Which Software is used for EOI",
    "options": [
      "OES",
      "ERA",
      "SOLAR",
      "None"
    ],
    "answer": 2,
    "explanation": "The Correct Answer is SOLAR"
  },
  {
    "id": 85,
    "question": "Which Software is used for Exam Schedule",
    "options": [
      "OES",
      "ERA",
      "SOLAR",
      "None"
    ],
    "answer": 2,
    "explanation": "The Correct Answer is SOLAR"
  },
  {
    "id": 86,
    "question": "Which Software is used for Attendance",
    "options": [
      "OES",
      "BizClient",
      "SOLAR",
      "None"
    ],
    "answer": 1,
    "explanation": "The Correct Answer is BizClient"
  },
  {
    "id": 87,
    "question": "Which is mandatory for learner confirmation",
    "options": [
      "Attendance",
      "Payment",
      "Both",
      "None"
    ],
    "answer": 2,
    "explanation": "The Correct Answer is Both"
  },
  {
    "id": 88,
    "question": "What is the minimum Attendance required",
    "options": [
      "75%",
      "80%",
      "85%",
      "None"
    ],
    "answer": 0,
    "explanation": "The Correct Answer is 75%"
  },
  {
    "id": 89,
    "question": "What is the minimum passing marks",
    "options": [
      "20",
      "30",
      "40",
      "None"
    ],
    "answer": 0,
    "explanation": "The Correct Answer is 20"
  },
  {
    "id": 90,
    "question": "What is the Total Marks of MS-CIT Learners",
    "options": [
      "50",
      "100",
      "150",
      "None"
    ],
    "answer": 1,
    "explanation": "The Correct Answer is 100"
  }
]