[
  {
    "id": 211,
    "question": "Can an existing Super Performing ALC apply for a new center in another district with preference?",
    "options": [
      "Yes",
      "No",
      "Depends on the District",
      "Only if they pay double fee"
    ],
    "answer": 1,
    "explanation": "The correct answer is: No. Preference is only for the same LLC region or District."
  },
  {
    "id": 212,
    "question": "What is the 'Performance Guarantee Amount'?",
    "options": [
      "A fee paid by students",
      "An amount paid by AO to register, kept with MKCL",
      "A salary for the coordinator",
      "A fine for low admissions"
    ],
    "answer": 1,
    "explanation": "The correct answer is: An amount paid by AO to register, kept with MKCL."
  },
  {
    "id": 213,
    "question": "Who is exempt from paying the Performance Guarantee Amount?",
    "options": [
      "Private Computer Institutes",
      "Educational Institutes (Schools & Colleges)",
      "Cyber Cafes",
      "NGOs"
    ],
    "answer": 1,
    "explanation": "The correct answer is: Educational Institutes (Schools & Colleges)."
  },
  {
    "id": 214,
    "question": "What is the total duration of the MS-CIT Course?",
    "options": [
      "1 Month",
      "2 Months",
      "3 Months",
      "6 Months"
    ],
    "answer": 1,
    "explanation": "The correct answer is: 3 Months (144 Hours)."
  },
  {
    "id": 215,
    "question": "What are the three languages in which MS-CIT course is available?",
    "options": [
      "English, Marathi, Gujarati",
      "English, Hindi, Urdu",
      "English, Marathi, Hindi",
      "English, Marathi, Sanskrit"
    ],
    "answer": 2,
    "explanation": "The correct answer is: English, Marathi, Hindi."
  },
  {
    "id": 216,
    "question": "What is the passing mark for the MS-CIT Final Online Examination (Students)?",
    "options": [
      "18 Marks",
      "20 Marks",
      "25 Marks",
      "35 Marks"
    ],
    "answer": 1,
    "explanation": "The correct answer is: 20 Marks out of 50."
  },
  {
    "id": 217,
    "question": "How many internal marks are allocated in the MS-CIT course?",
    "options": [
      "20 Marks",
      "30 Marks",
      "50 Marks",
      "100 Marks"
    ],
    "answer": 2,
    "explanation": "The correct answer is: 50 Marks. These are based on session completion and challenges."
  },
  {
    "id": 218,
    "question": "What is the full form of CCTP?",
    "options": [
      "Certificate of Computer Training Program",
      "Certificate of Computer Typing Proficiency",
      "Central Computer Technical Program",
      "Course for Computer Typing Professionals"
    ],
    "answer": 1,
    "explanation": "The correct answer is: Certificate of Computer Typing Proficiency."
  },
  {
    "id": 219,
    "question": "Who certifies the CCTP course?",
    "options": [
      "MKCL only",
      "MSBTE only",
      "Jointly by MKCL and MSBTE",
      "YCMOU"
    ],
    "answer": 2,
    "explanation": "The correct answer is: Jointly by MKCL and MSBTE."
  },
  {
    "id": 220,
    "question": "What is the typing speed option available in CCTP?",
    "options": [
      "10 WPM and 20 WPM",
      "30 WPM and 40 WPM",
      "50 WPM and 60 WPM",
      "Any speed"
    ],
    "answer": 1,
    "explanation": "The correct answer is: 30 WPM and 40 WPM."
  },
  {
    "id": 221,
    "question": "What keyboard layout is used in CCTP?",
    "options": [
      "Dvorak",
      "Remington",
      "Inscript",
      "Phonetic"
    ],
    "answer": 1,
    "explanation": "The correct answer is: Remington."
  },
  {
    "id": 222,
    "question": "Who is eligible for CCTP?",
    "options": [
      "Any 10th pass student",
      "Only IT professionals",
      "MS-CIT learners confirmed for the exam",
      "Center Coordinators only"
    ],
    "answer": 2,
    "explanation": "The correct answer is: MS-CIT learners confirmed for the exam."
  },
  {
    "id": 223,
    "question": "Which item is NOT part of the mandatory Counseling Area setup?",
    "options": [
      "Notice Board",
      "Enquiry Register",
      "Table and Chairs",
      "Projector"
    ],
    "answer": 3,
    "explanation": "The correct answer is: Projector. This is required in the Lecture Room, not the Counseling Area."
  },
  {
    "id": 224,
    "question": "What is the mandatory identity document for New Center Registration finalization in 2026?",
    "options": [
      "Aadhaar Card",
      "Passport",
      "Electricity Bill",
      "Rent Agreement"
    ],
    "answer": 0,
    "explanation": "The correct answer is: Aadhaar Card. Both PAN and Aadhaar are mandatory."
  },
  {
    "id": 225,
    "question": "What is the standard student fee for MS-CIT in Single Installment (prior to June 2025 revision)?",
    "options": [
      "Rs. 4,000/-",
      "Rs. 4,500/-",
      "Rs. 5,000/-",
      "Rs. 5,500/-"
    ],
    "answer": 1,
    "explanation": "The correct answer is: Rs. 4,500/- (Note: Fees may vary by region/date, but this is the standard base)."
  },
  {
    "id": 226,
    "question": "Does the student fee include the Examination and Certification fee?",
    "options": [
      "No, paid separately",
      "Yes, it is inclusive",
      "Only Certification is included",
      "Only Exam is included"
    ],
    "answer": 1,
    "explanation": "The correct answer is: Yes, it is inclusive."
  },
  {
    "id": 227,
    "question": "What is the 'MFO' component in the fee structure?",
    "options": [
      "Master Franchisee Office",
      "MKCL fee Only",
      "Monthly Fee Option",
      "Maintenance Fee Organization"
    ],
    "answer": 1,
    "explanation": "The correct answer is: MKCL fee Only (often referred to as MKCL's share)."
  },
  {
    "id": 228,
    "question": "What is the minimum age requirement for a student to join MS-CIT?",
    "options": [
      "10 years",
      "15 years",
      "18 years",
      "No specific age limit (preferably 5th Std pass)"
    ],
    "answer": 3,
    "explanation": "The correct answer is: No specific age limit (preferably 5th Std pass)."
  },
  {
    "id": 229,
    "question": "Which application is used by learners to access the e-book?",
    "options": [
      "MKCL ERA",
      "MKCL Learner App",
      "SOLAR App",
      "MS-CIT App"
    ],
    "answer": 1,
    "explanation": "The correct answer is: MKCL Learner App."
  },
  {
    "id": 230,
    "question": "What is the ERA in the context of MS-CIT?",
    "options": [
      "Education Registration Agency",
      "eLearning Revolution for All",
      "Electronic Read Access",
      "Exam Result Analysis"
    ],
    "answer": 1,
    "explanation": "The correct answer is: eLearning Revolution for All (MKCL's learning framework)."
  },
  {
    "id": 231,
    "question": "Can a center use a 'DG Set' for power backup?",
    "options": [
      "No",
      "Yes, it is optional",
      "Yes, it is mandatory",
      "Only for the server"
    ],
    "answer": 1,
    "explanation": "The correct answer is: Yes, it is optional. UPS/Inverter is compulsory."
  },
  {
    "id": 232,
    "question": "What is the minimum number of USB ports required on the Server?",
    "options": [
      "2",
      "3",
      "4",
      "6"
    ],
    "answer": 1,
    "explanation": "The correct answer is: 3."
  },
  {
    "id": 233,
    "question": "Does the Center Coordinator need to clear the ONCET exam?",
    "options": [
      "No, only faculty needs to",
      "Yes, mandatory",
      "Optional",
      "Only if they teach"
    ],
    "answer": 1,
    "explanation": "The correct answer is: Yes, mandatory."
  },
  {
    "id": 234,
    "question": "What is the total time duration for the CCTP typing test?",
    "options": [
      "5 Minutes",
      "10 Minutes",
      "15 Minutes",
      "30 Minutes"
    ],
    "answer": 1,
    "explanation": "The correct answer is: 10 Minutes."
  },
  {
    "id": 235,
    "question": "Which browser is part of the MS-CIT Practical Exam syllabus?",
    "options": [
      "Mozilla Firefox",
      "Google Chrome / Microsoft Edge",
      "Safari",
      "Opera"
    ],
    "answer": 1,
    "explanation": "The correct answer is: Google Chrome / Microsoft Edge."
  },
  {
    "id": 236,
    "question": "What is the difficulty level distribution in the MS-CIT Final Exam?",
    "options": [
      "All questions are same level",
      "Level 1 (Low), Level 2 (Medium), Level 3 (High)",
      "Only Easy and Hard",
      "Random"
    ],
    "answer": 1,
    "explanation": "The correct answer is: Level 1 (Low), Level 2 (Medium), Level 3 (High)."
  },
  {
    "id": 237,
    "question": "How many Practical questions are there in the MS-CIT Final Exam?",
    "options": [
      "15",
      "25",
      "35",
      "50"
    ],
    "answer": 2,
    "explanation": "The correct answer is: 35 Practical Questions."
  },
  {
    "id": 238,
    "question": "How many Objective questions are there in the MS-CIT Final Exam?",
    "options": [
      "15",
      "20",
      "35",
      "50"
    ],
    "answer": 0,
    "explanation": "The correct answer is: 15 Objective Questions."
  },
  {
    "id": 239,
    "question": "Is there negative marking in the ONCET exam?",
    "options": [
      "Yes, 0.25 per wrong answer",
      "Yes, 0.5 per wrong answer",
      "No negative marking",
      "Yes, only for Faculty"
    ],
    "answer": 2,
    "explanation": "The correct answer is: No negative marking."
  },
  {
    "id": 240,
    "question": "What happens if a Learning Facilitator fails the ONCET exam?",
    "options": [
      "They can re-appear immediately",
      "The AO may be disqualified if no other LF passes",
      "They pay a fine",
      "They are demoted"
    ],
    "answer": 1,
    "explanation": "The correct answer is: The AO may be disqualified if no other LF passes. At least one LF must clear it."
  }
]